cas_server/__init__.py
cas_server/admin.py
cas_server/apps.py
cas_server/auth.py
cas_server/cas.py
cas_server/default_settings.py
cas_server/federate.py
cas_server/forms.py
cas_server/models.py
cas_server/urls.py
cas_server/utils.py
cas_server/views.py
cas_server/locale/fr/LC_MESSAGES/django.mo
cas_server/locale/fr/LC_MESSAGES/django.po
cas_server/locale/nl/LC_MESSAGES/django.mo
cas_server/locale/nl/LC_MESSAGES/django.po
cas_server/locale/pt_BR/django.mo
cas_server/locale/pt_BR/django.po
cas_server/locale/zh_Hans/LC_MESSAGES/django.mo
cas_server/locale/zh_Hans/LC_MESSAGES/django.po
cas_server/management/__init__.py
cas_server/management/commands/__init__.py
cas_server/management/commands/cas_clean_federate.py
cas_server/management/commands/cas_clean_sessions.py
cas_server/management/commands/cas_clean_tickets.py
cas_server/migrations/0001_squashed_0013_auto_20170329_1748.py
cas_server/migrations/__init__.py
cas_server/static/cas_server/cas.js
cas_server/static/cas_server/favicon.ico
cas_server/static/cas_server/functions.js
cas_server/static/cas_server/logo.png
cas_server/static/cas_server/logo.svg
cas_server/static/cas_server/bs3/styles.css
cas_server/static/cas_server/bs4/fa-lock.svg
cas_server/static/cas_server/bs4/fa-user.svg
cas_server/static/cas_server/bs4/styles.css
cas_server/templates/cas_server/proxy.xml
cas_server/templates/cas_server/samlValidate.xml
cas_server/templates/cas_server/samlValidateError.xml
cas_server/templates/cas_server/serviceValidate.xml
cas_server/templates/cas_server/serviceValidateError.xml
cas_server/templates/cas_server/bs3/base.html
cas_server/templates/cas_server/bs3/form.html
cas_server/templates/cas_server/bs3/logged.html
cas_server/templates/cas_server/bs3/login.html
cas_server/templates/cas_server/bs3/logout.html
cas_server/templates/cas_server/bs3/warn.html
cas_server/templates/cas_server/bs4/base.html
cas_server/templates/cas_server/bs4/form.html
cas_server/templates/cas_server/bs4/logged.html
django_cas_server-3.1.0.dist-info/LICENSE
django_cas_server-3.1.0.dist-info/METADATA
django_cas_server-3.1.0.dist-info/WHEEL
django_cas_server-3.1.0.dist-info/top_level.txt
django_cas_server-3.1.0.dist-info/RECORD
