Metadata-Version: 2.1
Name: django-cas-server
Version: 3.1.0
Summary: A Django Central Authentication Service server implementing the CAS Protocol 3.0 Specification
Home-page: https://github.com/nitmir/django-cas-server
Download-URL: https://github.com/nitmir/django-cas-server/releases/latest
Author: Valentin Samir
Author-email: valentin.samir@crans.org
License: GPLv3
Keywords: django,cas,cas3,server,sso,single sign-on,authentication,auth
Classifier: Environment :: Web Environment
Classifier: Development Status :: 5 - Production/Stable
Classifier: Framework :: Django
Classifier: Framework :: Django :: 1.11
Classifier: Framework :: Django :: 2.2
Classifier: Framework :: Django :: 3.2
Classifier: Framework :: Django :: 4.2
Classifier: Framework :: Django :: 5.2
Classifier: Intended Audience :: Developers
Classifier: Intended Audience :: System Administrators
Classifier: License :: OSI Approved :: GNU General Public License v3 (GPLv3)
Classifier: Operating System :: OS Independent
Classifier: Programming Language :: Python
Classifier: Programming Language :: Python :: 3
Classifier: Programming Language :: Python :: 3.6
Classifier: Programming Language :: Python :: 3.7
Classifier: Programming Language :: Python :: 3.8
Classifier: Programming Language :: Python :: 3.9
Classifier: Programming Language :: Python :: 3.10
Classifier: Programming Language :: Python :: 3.11
Classifier: Programming Language :: Python :: 3.12
Classifier: Programming Language :: Python :: 3.13
Classifier: Topic :: Software Development :: Libraries :: Python Modules
Classifier: Topic :: Internet :: WWW/HTTP
Classifier: Topic :: Internet :: WWW/HTTP :: Dynamic Content
Classifier: Topic :: System :: Systems Administration :: Authentication/Directory
License-File: LICENSE
Requires-Dist: Django (<5.3,>=1.11)
Requires-Dist: lxml (>=3.4)
Requires-Dist: requests (>=2.4)
Requires-Dist: requests-futures (>=0.9.5)
